MANIFEST.in
README.rst
requirements-dev.txt
requirements.txt
setup.cfg
setup.py
django_tasker/__init__.py
django_tasker/admin.py
django_tasker/apps.py
django_tasker/decoration.py
django_tasker/exceptions.py
django_tasker/models.py
django_tasker/worker.py
django_tasker.egg-info/PKG-INFO
django_tasker.egg-info/SOURCES.txt
django_tasker.egg-info/dependency_links.txt
django_tasker.egg-info/entry_points.txt
django_tasker.egg-info/requires.txt
django_tasker.egg-info/top_level.txt
django_tasker/migrations/0001_initial.py
django_tasker/migrations/0002_auto_20161221_1254.py
django_tasker/migrations/0003_auto_20161225_1223.py
django_tasker/migrations/0004_auto_20170102_1510.py
django_tasker/migrations/0005_auto_20170107_2302.py
django_tasker/migrations/0006_auto_20170120_1122.py
django_tasker/migrations/0007_auto_20170505_1526.py
django_tasker/migrations/0008_taskinfo_name.py
django_tasker/migrations/0009_auto_20170512_2240.py
django_tasker/migrations/0010_auto_20170523_1554.py
django_tasker/migrations/0011_auto_20170609_1308.py
django_tasker/migrations/0012_auto_20170609_1820.py
django_tasker/migrations/__init__.py